language_local/__init__.py
language_local/lang_code.py
language_local-0.0.9.dist-info/METADATA
language_local-0.0.9.dist-info/WHEEL
language_local-0.0.9.dist-info/top_level.txt
language_local-0.0.9.dist-info/RECORD
