Metadata-Version: 2.1
Name: language-local
Version: 0.0.9
Home-page: https://github.com/circles-zone/language-local-python-package
Author: Circles
Author-email: info@circles.life
Classifier: Programming Language :: Python :: 3
Classifier: License :: Other/Proprietary License
Classifier: Operating System :: OS Independent
